{
	"Hi": {"message": "Hi","description": ""},
	"Welcome": {"message": "Welcome {0}","description": ""},
	"UserList": {"message": "User List","description": ""},
	"Error": {"message": "Hata","description": ""},
	"Warning": {"message": "Uyarı","description": ""},
	"NoPermission": {"message": "NoPermission","description": ""},
	"Edit": {"message": "Edit" ,"description": ""},
	"Delete": {"message": "Sil" ,"description": ""},
	"CurrentPaging": {"message": "{from}-{to} Toplam {count}" ,"description": ""},
	"Row": {"message": "Satır" ,"description": ""},
	"LineSelected": {"message": "{0} Satır (s) Seçildi" ,"description": ""},
	"Search": {"message": "Ara" ,"description": ""},
	"Actions": {"message": "İşlemler" ,"description": ""},	
	"RecordNotFound": {"message": "Kayıt Bulunamadı!" ,"description": ""},
	"Filter": {"message": "Filtre" ,"description": ""},	
	"Yes": {"message": "Evet" ,"description": ""},
	"No": {"message": "Hayır" ,"description": ""},
	"Cancel": {"message": "İptal" ,"description": ""},
	"Ok": {"message": "Tamam" ,"description": ""},
	"Close": {"message": "Kapat" ,"description": ""},
	"Loading": {"message": "Yükleniyor..." ,"description": ""},
} 
